polywrap_core/__init__.py
polywrap_core/py.typed
polywrap_core/types/__init__.py
polywrap_core/types/clean_resolution_step.py
polywrap_core/types/client.py
polywrap_core/types/config.py
polywrap_core/types/errors.py
polywrap_core/types/file_reader.py
polywrap_core/types/invocable.py
polywrap_core/types/invoke_options.py
polywrap_core/types/invoker.py
polywrap_core/types/invoker_client.py
polywrap_core/types/uri.py
polywrap_core/types/uri_package.py
polywrap_core/types/uri_package_wrapper.py
polywrap_core/types/uri_resolution_context.py
polywrap_core/types/uri_resolution_step.py
polywrap_core/types/uri_resolver.py
polywrap_core/types/uri_resolver_handler.py
polywrap_core/types/uri_wrapper.py
polywrap_core/types/wrap_package.py
polywrap_core/types/wrapper.py
polywrap_core/utils/__init__.py
polywrap_core/utils/build_clean_uri_history.py
polywrap_core/utils/get_env_from_resolution_path.py
polywrap_core/utils/get_implementations.py
polywrap_core-0.1.2.dist-info/METADATA
polywrap_core-0.1.2.dist-info/WHEEL
polywrap_core-0.1.2.dist-info/RECORD
